{"entries":[{"id":"moving_audience","name":"moving_audience","description":"Filters players performing any movement action or directional input.","color":"#4CAF50","icon":"game-icons:run","className":"me.yellowhead.audience.movement.MovingAudience","extension":"PlayerInputAudiences","tags":["audience_filter","audience","manifest","placeholder","entry"],"dataBlueprint":{"kind":"object","fields":{"id":{"kind":"primitive","type":"string"},"name":{"kind":"primitive","type":"string"},"children":{"kind":"list","type":{"kind":"custom","modifiers":[{"name":"entry","data":"audience"}],"editor":"ref","shape":{"kind":"primitive","type":"string"}}},"inverted":{"kind":"primitive","modifiers":[{"name":"help","data":"The audience will be the players that do not match the criteria."}],"type":"boolean"}}},"contextKeys":[],"modifiers":[]},{"id":"jump_audience","name":"jump_audience","description":"Filters players pressing jump (space bar).","color":"#4CAF50","icon":"game-icons:jump-across","className":"me.yellowhead.audience.movement.actions.JumpingAudience","extension":"PlayerInputAudiences","tags":["audience_filter","audience","manifest","placeholder","entry"],"dataBlueprint":{"kind":"object","fields":{"id":{"kind":"primitive","type":"string"},"name":{"kind":"primitive","type":"string"},"children":{"kind":"list","type":{"kind":"custom","modifiers":[{"name":"entry","data":"audience"}],"editor":"ref","shape":{"kind":"primitive","type":"string"}}},"inverted":{"kind":"primitive","modifiers":[{"name":"help","data":"The audience will be the players that do not match the criteria."}],"type":"boolean"}}},"contextKeys":[],"modifiers":[]},{"id":"sneaking_audience","name":"sneaking_audience","description":"Filters players to only those who are sneaking (crouching), supports ticking and children audiences.","color":"#4CAF50","icon":"fluent:slow-mode-24-regular","className":"me.yellowhead.audience.movement.actions.SneakingAudience","extension":"PlayerInputAudiences","tags":["audience_filter","audience","manifest","placeholder","entry"],"dataBlueprint":{"kind":"object","fields":{"id":{"kind":"primitive","type":"string"},"name":{"kind":"primitive","type":"string"},"children":{"kind":"list","type":{"kind":"custom","modifiers":[{"name":"entry","data":"audience"}],"editor":"ref","shape":{"kind":"primitive","type":"string"}}},"inverted":{"kind":"primitive","modifiers":[{"name":"help","data":"The audience will be the players that do not match the criteria."}],"type":"boolean"}}},"contextKeys":[],"modifiers":[]},{"id":"sprinting_audience","name":"sprinting_audience","description":"Filters players to only those who are sprinting. Supports ticking and child audiences.","color":"#4CAF50","icon":"game-icons:run","className":"me.yellowhead.audience.movement.actions.SprintingAudience","extension":"PlayerInputAudiences","tags":["audience_filter","audience","manifest","placeholder","entry"],"dataBlueprint":{"kind":"object","fields":{"id":{"kind":"primitive","type":"string"},"name":{"kind":"primitive","type":"string"},"children":{"kind":"list","type":{"kind":"custom","modifiers":[{"name":"entry","data":"audience"}],"editor":"ref","shape":{"kind":"primitive","type":"string"}}},"inverted":{"kind":"primitive","modifiers":[{"name":"help","data":"The audience will be the players that do not match the criteria."}],"type":"boolean"}}},"contextKeys":[],"modifiers":[]},{"id":"backward_audience","name":"backward_audience","description":"Filters players pressing backward (S key).","color":"#4CAF50","icon":"mi:arrow-down","className":"me.yellowhead.audience.movement.directional.BackwardAudience","extension":"PlayerInputAudiences","tags":["audience_filter","audience","manifest","placeholder","entry"],"dataBlueprint":{"kind":"object","fields":{"id":{"kind":"primitive","type":"string"},"name":{"kind":"primitive","type":"string"},"children":{"kind":"list","type":{"kind":"custom","modifiers":[{"name":"entry","data":"audience"}],"editor":"ref","shape":{"kind":"primitive","type":"string"}}},"inverted":{"kind":"primitive","modifiers":[{"name":"help","data":"The audience will be the players that do not match the criteria."}],"type":"boolean"}}},"contextKeys":[],"modifiers":[]},{"id":"forward_audience","name":"forward_audience","description":"Filters players pressing forward (W key).","color":"#4CAF50","icon":"mi:arrow-up","className":"me.yellowhead.audience.movement.directional.ForwardAudience","extension":"PlayerInputAudiences","tags":["audience_filter","audience","manifest","placeholder","entry"],"dataBlueprint":{"kind":"object","fields":{"id":{"kind":"primitive","type":"string"},"name":{"kind":"primitive","type":"string"},"children":{"kind":"list","type":{"kind":"custom","modifiers":[{"name":"entry","data":"audience"}],"editor":"ref","shape":{"kind":"primitive","type":"string"}}},"inverted":{"kind":"primitive","modifiers":[{"name":"help","data":"The audience will be the players that do not match the criteria."}],"type":"boolean"}}},"contextKeys":[],"modifiers":[]},{"id":"left_audience","name":"left_audience","description":"Filters players pressing left (A key).","color":"#4CAF50","icon":"mi:arrow-left","className":"me.yellowhead.audience.movement.directional.LeftAudience","extension":"PlayerInputAudiences","tags":["audience_filter","audience","manifest","placeholder","entry"],"dataBlueprint":{"kind":"object","fields":{"id":{"kind":"primitive","type":"string"},"name":{"kind":"primitive","type":"string"},"children":{"kind":"list","type":{"kind":"custom","modifiers":[{"name":"entry","data":"audience"}],"editor":"ref","shape":{"kind":"primitive","type":"string"}}},"inverted":{"kind":"primitive","modifiers":[{"name":"help","data":"The audience will be the players that do not match the criteria."}],"type":"boolean"}}},"contextKeys":[],"modifiers":[]},{"id":"right_audience","name":"right_audience","description":"Filters players pressing right (D key).","color":"#4CAF50","icon":"mi:arrow-right","className":"me.yellowhead.audience.movement.directional.RightAudience","extension":"PlayerInputAudiences","tags":["audience_filter","audience","manifest","placeholder","entry"],"dataBlueprint":{"kind":"object","fields":{"id":{"kind":"primitive","type":"string"},"name":{"kind":"primitive","type":"string"},"children":{"kind":"list","type":{"kind":"custom","modifiers":[{"name":"entry","data":"audience"}],"editor":"ref","shape":{"kind":"primitive","type":"string"}}},"inverted":{"kind":"primitive","modifiers":[{"name":"help","data":"The audience will be the players that do not match the criteria."}],"type":"boolean"}}},"contextKeys":[],"modifiers":[]},{"id":"on_player_input","name":"on_player_input","description":"Triggers when a player performs a chosen input (jump, sprint, sneak, movement keys, drop, or swap hands).","color":"#FBB612","icon":"game-icons:abstract-016","className":"me.yellowhead.event.movement.PlayerInputEventEntry","extension":"PlayerInputAudiences","tags":["cancelable_event","event","trigger","entry"],"dataBlueprint":{"kind":"object","fields":{"id":{"kind":"primitive","type":"string"},"name":{"kind":"primitive","type":"string"},"triggers":{"kind":"list","modifiers":[{"name":"help","data":"The entries that will be fired after this entry."}],"type":{"kind":"custom","modifiers":[{"name":"entry","data":"triggerable"}],"editor":"ref","shape":{"kind":"primitive","type":"string"}}},"inputType":{"kind":"custom","modifiers":[{"name":"help","data":"If set, only triggers when this specific input is performed."}],"default":{"enabled":false,"value":"JUMP"},"editor":"optional","shape":{"kind":"object","fields":{"enabled":{"kind":"primitive","type":"boolean"},"value":{"kind":"enum","values":["JUMP","SPRINT","SNEAK","FORWARD","BACKWARD","LEFT","RIGHT","DROP","SWAP_HANDS"]}}}},"heldItem":{"kind":"custom","modifiers":[{"name":"help","data":"Require the player to be holding this item."}],"default":{"enabled":false,"value":{"case":"custom_item","value":{}}},"editor":"optional","shape":{"kind":"object","fields":{"enabled":{"kind":"primitive","type":"boolean"},"value":{"kind":"custom","default":{"case":"custom_item","value":{}},"editor":"var","shape":{"kind":"custom","modifiers":[{"name":"contentMode","data":"com.typewritermc.engine.paper.content.modes.custom.HoldingItemContentMode"}],"default":{"case":"custom_item","value":{}},"editor":"item","shape":{"kind":"algebraic","cases":{"custom_item":{"kind":"object","modifiers":[{"name":"color","data":"#1E88E5"},{"name":"icon","data":"mdi:shape"}],"fields":{"components":{"kind":"list","type":{"kind":"algebraic","cases":{"amount":{"kind":"object","modifiers":[{"name":"color","data":"#1E88E5"},{"name":"icon","data":"fa6-solid:hashtag"}],"fields":{"amount":{"kind":"custom","default":1,"editor":"var","shape":{"kind":"primitive","modifiers":[{"name":"min","data":0}],"type":"integer"}}}},"flag":{"kind":"object","modifiers":[{"name":"color","data":"#1E88E5"},{"name":"icon","data":"material-symbols:flag"}],"fields":{"flag":{"kind":"enum","values":["HIDE_ENCHANTS","HIDE_ATTRIBUTES","HIDE_UNBREAKABLE","HIDE_DESTROYS","HIDE_PLACED_ON","HIDE_ADDITIONAL_TOOLTIP","HIDE_DYE","HIDE_ARMOR_TRIM","HIDE_STORED_ENCHANTS"]}}},"lore":{"kind":"object","modifiers":[{"name":"color","data":"#F57C00"},{"name":"icon","data":"flowbite:file-lines-solid"}],"fields":{"lore":{"kind":"custom","default":"","editor":"var","shape":{"kind":"primitive","modifiers":[{"name":"colored","data":null},{"name":"multiline","data":null},{"name":"placeholder","data":null}],"type":"string"}}}},"material":{"kind":"object","modifiers":[{"name":"color","data":"#1E88E5"},{"name":"icon","data":"fa6-solid:cube"}],"fields":{"material":{"kind":"custom","default":"AIR","editor":"var","shape":{"kind":"custom","modifiers":[{"name":"material_properties","data":"item"}],"default":"AIR","editor":"material","shape":{"kind":"primitive","type":"string"}}}}},"item_name":{"kind":"object","modifiers":[{"name":"color","data":"#F57C00"},{"name":"icon","data":"fa6-solid:tag"}],"fields":{"name":{"kind":"custom","default":"","editor":"var","shape":{"kind":"primitive","modifiers":[{"name":"colored","data":null},{"name":"placeholder","data":null}],"type":"string"}}}}}}}}},"serialized_item":{"kind":"custom","modifiers":[{"name":"color","data":"#F57C00"},{"name":"icon","data":"mingcute:file-code-fill"}],"default":{},"editor":"serialized_item","shape":{"kind":"object","fields":{"material":{"kind":"custom","default":"AIR","editor":"material","shape":{"kind":"primitive","type":"string"}},"name":{"kind":"primitive","type":"string"},"amount":{"kind":"custom","default":1,"editor":"var","shape":{"kind":"primitive","type":"integer"}},"bytes":{"kind":"primitive","type":"string"}}}}}}}}}}},"cancel":{"kind":"custom","modifiers":[{"name":"help","data":"\n        Cancel the event when triggered.\n        If set to false, it will not modify the event.\n        "}],"default":false,"editor":"var","shape":{"kind":"primitive","type":"boolean"}}}},"contextKeys":[{"name":"INPUT_TYPE","klassName":"me.yellowhead.event.movement.PlayerInputContextKeys","blueprint":{"kind":"enum","values":["JUMP","SPRINT","SNEAK","FORWARD","BACKWARD","LEFT","RIGHT","DROP","SWAP_HANDS"]}},{"name":"IS_JUMP","klassName":"me.yellowhead.event.movement.PlayerInputContextKeys","blueprint":{"kind":"primitive","type":"boolean"}},{"name":"IS_SPRINT","klassName":"me.yellowhead.event.movement.PlayerInputContextKeys","blueprint":{"kind":"primitive","type":"boolean"}},{"name":"IS_SNEAK","klassName":"me.yellowhead.event.movement.PlayerInputContextKeys","blueprint":{"kind":"primitive","type":"boolean"}},{"name":"IS_FORWARD","klassName":"me.yellowhead.event.movement.PlayerInputContextKeys","blueprint":{"kind":"primitive","type":"boolean"}},{"name":"IS_BACKWARD","klassName":"me.yellowhead.event.movement.PlayerInputContextKeys","blueprint":{"kind":"primitive","type":"boolean"}},{"name":"IS_LEFT","klassName":"me.yellowhead.event.movement.PlayerInputContextKeys","blueprint":{"kind":"primitive","type":"boolean"}},{"name":"IS_RIGHT","klassName":"me.yellowhead.event.movement.PlayerInputContextKeys","blueprint":{"kind":"primitive","type":"boolean"}},{"name":"IS_DROP","klassName":"me.yellowhead.event.movement.PlayerInputContextKeys","blueprint":{"kind":"primitive","type":"boolean"}},{"name":"IS_SWAP_HANDS","klassName":"me.yellowhead.event.movement.PlayerInputContextKeys","blueprint":{"kind":"primitive","type":"boolean"}}],"modifiers":[]}],"entryListeners":[{"entryBlueprintId":"on_player_input","entryClassName":"me.yellowhead.event.movement.PlayerInputEventEntry","className":"me.yellowhead.event.movement.OnPlayerInputTypeKt","methodName":"onPlayerInput","priority":"NORMAL","ignoreCancelled":true,"arguments":["org.bukkit.event.player.PlayerInputEvent","com.typewritermc.core.entries.Query"]},{"entryBlueprintId":"on_player_input","entryClassName":"me.yellowhead.event.movement.PlayerInputEventEntry","className":"me.yellowhead.event.movement.OnPlayerInputTypeKt","methodName":"onPlayerDrop","priority":"NORMAL","ignoreCancelled":true,"arguments":["org.bukkit.event.player.PlayerDropItemEvent","com.typewritermc.core.entries.Query"]},{"entryBlueprintId":"on_player_input","entryClassName":"me.yellowhead.event.movement.PlayerInputEventEntry","className":"me.yellowhead.event.movement.OnPlayerInputTypeKt","methodName":"onPlayerSwapHands","priority":"NORMAL","ignoreCancelled":true,"arguments":["org.bukkit.event.player.PlayerSwapHandItemsEvent","com.typewritermc.core.entries.Query"]},{"entryBlueprintId":"on_player_input","entryClassName":"me.yellowhead.event.movement.PlayerInputEventEntry","className":"me.yellowhead.event.movement.OnPlayerInputTypeKt","methodName":"onInventoryDrop","priority":"NORMAL","ignoreCancelled":true,"arguments":["org.bukkit.event.inventory.InventoryClickEvent","com.typewritermc.core.entries.Query"]}],"typewriterCommands":[],"dependencyInjections":[],"globalContextKeys":[],"extension":{"name":"PlayerInputAudiences","shortDescription":"Detect and filter players based on key inputs","description":"Provides audience filters for detecting player inputs in real-time, including movement (W/A/S/D) and actions (jump, sneak, sprint).Useful for custom mechanics, AFK detection, or gameplay triggers.","engineVersion":"0.9.0-beta-163","channel":"BETA","paper":{},"pluginVersion":"1.3.0","version":"0.9.0-beta-163","namespace":"yellowhead","dependencies":[]}}